odoo/addons/beesdoo_stock/README.rst
odoo/addons/beesdoo_stock/__init__.py
odoo/addons/beesdoo_stock/__manifest__.py
odoo/addons/beesdoo_stock/models/__init__.py
odoo/addons/beesdoo_stock/models/stock.py
odoo/addons/beesdoo_stock/readme/CONTRIBUTORS.rst
odoo/addons/beesdoo_stock/readme/DESCRIPTION.rst
odoo/addons/beesdoo_stock/static/description/index.html
odoo/addons/beesdoo_stock/views/stock_view.xml
odoo12_addon_beesdoo_stock-12.0.1.0.0.99.dev6.dist-info/METADATA
odoo12_addon_beesdoo_stock-12.0.1.0.0.99.dev6.dist-info/WHEEL
odoo12_addon_beesdoo_stock-12.0.1.0.0.99.dev6.dist-info/top_level.txt
odoo12_addon_beesdoo_stock-12.0.1.0.0.99.dev6.dist-info/RECORD
