Metadata-Version: 2.1
Name: odoo12-addon-beesdoo-stock
Version: 12.0.1.0.0.99.dev6
Summary: Enable action on multiple products of a stock receipt
Home-page: https://www.coopiteasy.be
Author: Coop IT Easy SCRLfs
License: AGPL-3
Platform: UNKNOWN
Classifier: Programming Language :: Python
Classifier: Framework :: Odoo
Classifier: License :: OSI Approved :: GNU Affero General Public License v3
Requires-Python: >=3.5
Requires-Dist: odoo (<12.1dev,>=12.0a)
